ftpvl/__init__.py
ftpvl/evaluation.py
ftpvl/fetchers.py
ftpvl/helpers.py
ftpvl/processors.py
ftpvl/settings.py
ftpvl/styles.py
ftpvl/visualizers.py
ftpvl_beta-0.2.1.dist-info/LICENSE
ftpvl_beta-0.2.1.dist-info/METADATA
ftpvl_beta-0.2.1.dist-info/WHEEL
ftpvl_beta-0.2.1.dist-info/top_level.txt
ftpvl_beta-0.2.1.dist-info/RECORD
