Metadata-Version: 2.1
Name: ftpvl-beta
Version: 0.2.1
Summary: A visualization library for FPGA Tool Performance
Home-page: https://github.com/TypingKoala/FPGA-Tool-Performance-Visualization-Library
Author: Johnny Bui
Author-email: me@johnnybui.com
License: MIT
Platform: UNKNOWN
Classifier: License :: OSI Approved :: MIT License
Classifier: Programming Language :: Python
Classifier: Programming Language :: Python :: 3
Classifier: Programming Language :: Python :: 3.6
Classifier: Programming Language :: Python :: Implementation :: CPython
Classifier: Programming Language :: Python :: Implementation :: PyPy
Requires-Python: >=3.6.0
Requires-Dist: seaborn
Requires-Dist: pandas
Requires-Dist: jinja2
